grai_source_openlineage/__init__.py
grai_source_openlineage/adapters.py
grai_source_openlineage/base.py
grai_source_openlineage/models.py
grai_source_openlineage/package_definitions.py
grai_source_openlineage/processor.py
grai_source_openlineage-0.1.0a1.dist-info/METADATA
grai_source_openlineage-0.1.0a1.dist-info/WHEEL
grai_source_openlineage-0.1.0a1.dist-info/RECORD
