Metadata-Version: 2.1
Name: grai-source-openlineage
Version: 0.1.0a1
Summary: 
Home-page: https://www.grai.io/
License: Elastic-2.0
Author: Edward Louth
Author-email: edward@grai.io
Requires-Python: >=3.8,<4.0
Classifier: License :: Other/Proprietary License
Classifier: Programming Language :: Python :: 3
Classifier: Programming Language :: Python :: 3.8
Classifier: Programming Language :: Python :: 3.9
Classifier: Programming Language :: Python :: 3.10
Classifier: Programming Language :: Python :: 3.11
Requires-Dist: grai-schemas (>=0.2.6,<0.3.0)
Requires-Dist: pydantic (>=1.9.1,<2.0.0)
Project-URL: Documentation, https://docs.grai.io/
Project-URL: Repository, https://github.com/grai-io/grai-core/tree/master/grai-integrations/source-openlineage
